chipignite/__init__.py
chipignite-0.0.1.dist-info/LICENSE
chipignite-0.0.1.dist-info/METADATA
chipignite-0.0.1.dist-info/WHEEL
chipignite-0.0.1.dist-info/top_level.txt
chipignite-0.0.1.dist-info/RECORD
