Metadata-Version: 2.1
Name: chipignite
Version: 0.0.1
Summary: A python package for all things chipignite
Home-page: https://github.com/yourusername/your-repo-name
Author: Efabless corp.
Author-email: shuttle@efabless.com
License: UNKNOWN
Platform: UNKNOWN
Classifier: Programming Language :: Python :: 3
Classifier: License :: OSI Approved :: MIT License
Classifier: Operating System :: OS Independent
Requires-Python: >=3.6
License-File: LICENSE
